bidsphysio.acq2bids-21.6.24-py3.8-nspkg.pth
bidsphysio/acq2bids/__init__.py
bidsphysio/acq2bids/acq2bidsphysio.py
bidsphysio/acq2bids/acqsession2bids.py
bidsphysio/acq2bids/info.py
tests/__init__.py
tests/test_acq2bidsphysio.py
tests/test_acqsession2bids.py
tests/utils.py
bidsphysio.acq2bids-21.6.24.dist-info/METADATA
bidsphysio.acq2bids-21.6.24.dist-info/WHEEL
bidsphysio.acq2bids-21.6.24.dist-info/entry_points.txt
bidsphysio.acq2bids-21.6.24.dist-info/namespace_packages.txt
bidsphysio.acq2bids-21.6.24.dist-info/top_level.txt
bidsphysio.acq2bids-21.6.24.dist-info/RECORD
