Metadata-Version: 2.1
Name: bidsphysio.acq2bids
Version: 21.6.24
Summary: AcqKnowledge-to-BIDS Converter
Home-page: UNKNOWN
Author: Pablo Velasco
Author-email: pablo.velasco@nyu.edu
License: MIT
Platform: UNKNOWN
Classifier: Environment :: Console
Classifier: Intended Audience :: Science/Research
Classifier: License :: OSI Approved :: MIT License
Classifier: Programming Language :: Python :: 3.6
Classifier: Programming Language :: Python :: 3.7
Classifier: Programming Language :: Python :: 3.8
Classifier: Topic :: Scientific/Engineering
Requires-Python: >=3.6
Requires-Dist: bidsphysio.base (>=21.5.27)
Requires-Dist: bidsphysio.session (>=21.06.24)
Requires-Dist: bioread[mat] (>=2.0.0)
Provides-Extra: all
Requires-Dist: pytest ; extra == 'all'
Provides-Extra: tests
Requires-Dist: pytest ; extra == 'tests'
